energyflow/__init__.py
energyflow/_version.py
energyflow/base.py
energyflow/efm.py
energyflow/efp.py
energyflow/emd.py
energyflow/gen.py
energyflow/measure.py
energyflow/obs.py
energyflow/algorithms/__init__.py
energyflow/algorithms/einsumfunc.py
energyflow/algorithms/integer_partitions.py
energyflow/algorithms/ve.py
energyflow/archs/__init__.py
energyflow/archs/archbase.py
energyflow/archs/cnn.py
energyflow/archs/dnn.py
energyflow/archs/efn.py
energyflow/archs/linear.py
energyflow/data/CMS2011AJets.json
energyflow/data/ZjetsDelphes.json
energyflow/data/efps_d_le_10.json.gz
energyflow/datasets/__init__.py
energyflow/datasets/mod.py
energyflow/datasets/qg_jets.py
energyflow/datasets/qg_nsubs.py
energyflow/datasets/zjets_delphes.py
energyflow/utils/__init__.py
energyflow/utils/data_utils.py
energyflow/utils/event_utils.py
energyflow/utils/fastjet_utils.py
energyflow/utils/generic_utils.py
energyflow/utils/graph_utils.py
energyflow/utils/image_utils.py
energyflow/utils/particle_utils.py
energyflow-1.4.0.dist-info/METADATA
energyflow-1.4.0.dist-info/WHEEL
energyflow-1.4.0.dist-info/licenses/LICENSE
energyflow-1.4.0.dist-info/RECORD
