Metadata-Version: 2.3
Name: EnergyFlow
Version: 1.4.0
Summary: Python package for the Energy Flow suite of particle physics tools
Project-URL: Homepage, https://energyflow.network
Project-URL: Issues, https://github.com/thaler-lab/EnergyFlow/issues
Project-URL: Source Code, https://github.com/thaler-lab/EnergyFlow
Author-email: "Patrick T. Komiske III" <pkomiske@mit.edu>
Maintainer-email: Rikab Gambhir <rikab@mit.edu>, Jordan Ashley <jordan.ashley@cern.ch>
License-File: LICENSE
Keywords: CMS,Deep Sets,EFM,EFN,EFP,EMD,Earth Mover Distance,Energy Flow Moment,Energy Flow Network,Energy Flow Polynomial,MOD,Open Data,PFN,Particle Flow Network,Wasserstein,architecture,collider,correlator,energy flow,energyflow,jets,metric,multigraph,neural network,open,physics,polynomial,substructure
Classifier: Development Status :: 5 - Production/Stable
Classifier: Intended Audience :: Developers
Classifier: Intended Audience :: Science/Research
Classifier: License :: OSI Approved :: GNU General Public License v3 (GPLv3)
Classifier: Natural Language :: English
Classifier: Operating System :: MacOS
Classifier: Operating System :: Microsoft :: Windows
Classifier: Operating System :: POSIX :: Linux
Classifier: Operating System :: Unix
Classifier: Programming Language :: C++
Classifier: Programming Language :: Python
Classifier: Programming Language :: Python :: 3
Classifier: Programming Language :: Python :: 3 :: Only
Classifier: Programming Language :: Python :: 3.9
Classifier: Programming Language :: Python :: 3.10
Classifier: Programming Language :: Python :: 3.11
Classifier: Programming Language :: Python :: 3.12
Classifier: Topic :: Scientific/Engineering
Classifier: Topic :: Scientific/Engineering :: Information Analysis
Classifier: Topic :: Scientific/Engineering :: Mathematics
Classifier: Topic :: Scientific/Engineering :: Physics
Classifier: Topic :: Software Development :: Libraries :: Python Modules
Requires-Python: >=3.9
Requires-Dist: h5py!=3.11.0,>=2.9.0
Requires-Dist: importlib-metadata>=1.4.0; python_version < '3.8'
Requires-Dist: numpy>=1.17.0
Requires-Dist: wasserstein>=1.0.1
Provides-Extra: all
Requires-Dist: igraph; extra == 'all'
Requires-Dist: scikit-learn; extra == 'all'
Requires-Dist: tensorflow>=2.5.0; extra == 'all'
Provides-Extra: archs
Requires-Dist: scikit-learn; extra == 'archs'
Requires-Dist: tensorflow>=2.5.0; extra == 'archs'
Provides-Extra: examples
Requires-Dist: matplotlib; extra == 'examples'
Requires-Dist: scikit-learn; extra == 'examples'
Requires-Dist: tensorflow>=2.5.0; extra == 'examples'
Provides-Extra: generation
Requires-Dist: igraph; extra == 'generation'
Provides-Extra: tests
Requires-Dist: igraph; extra == 'tests'
Requires-Dist: pot>=0.8.0; extra == 'tests'
Requires-Dist: pytest; extra == 'tests'
Requires-Dist: scikit-learn; extra == 'tests'
Requires-Dist: tensorflow>=2.5.0; extra == 'tests'
